enum_choices/__init__.py
enum_choices/choices.py
enum_choices-0.1.2.dist-info/WHEEL
enum_choices-0.1.2.dist-info/METADATA
enum_choices-0.1.2.dist-info/RECORD
